awslabs/__init__.py
awslabs/elasticache_mcp_server/__init__.py
awslabs/elasticache_mcp_server/context.py
awslabs/elasticache_mcp_server/main.py
awslabs/elasticache_mcp_server/common/__init__.py
awslabs/elasticache_mcp_server/common/connection.py
awslabs/elasticache_mcp_server/common/decorators.py
awslabs/elasticache_mcp_server/common/server.py
awslabs/elasticache_mcp_server/tools/__init__.py
awslabs/elasticache_mcp_server/tools/cc/__init__.py
awslabs/elasticache_mcp_server/tools/cc/connect.py
awslabs/elasticache_mcp_server/tools/cc/create.py
awslabs/elasticache_mcp_server/tools/cc/delete.py
awslabs/elasticache_mcp_server/tools/cc/describe.py
awslabs/elasticache_mcp_server/tools/cc/modify.py
awslabs/elasticache_mcp_server/tools/cc/parsers.py
awslabs/elasticache_mcp_server/tools/cc/processors.py
awslabs/elasticache_mcp_server/tools/ce/__init__.py
awslabs/elasticache_mcp_server/tools/ce/get_cost_and_usage.py
awslabs/elasticache_mcp_server/tools/cw/__init__.py
awslabs/elasticache_mcp_server/tools/cw/get_metric_statistics.py
awslabs/elasticache_mcp_server/tools/cwlogs/__init__.py
awslabs/elasticache_mcp_server/tools/cwlogs/create_log_group.py
awslabs/elasticache_mcp_server/tools/cwlogs/describe_log_groups.py
awslabs/elasticache_mcp_server/tools/cwlogs/describe_log_streams.py
awslabs/elasticache_mcp_server/tools/cwlogs/filter_log_events.py
awslabs/elasticache_mcp_server/tools/cwlogs/get_log_events.py
awslabs/elasticache_mcp_server/tools/firehose/__init__.py
awslabs/elasticache_mcp_server/tools/firehose/list_delivery_streams.py
awslabs/elasticache_mcp_server/tools/misc/__init__.py
awslabs/elasticache_mcp_server/tools/misc/batch_apply_update_action.py
awslabs/elasticache_mcp_server/tools/misc/batch_stop_update_action.py
awslabs/elasticache_mcp_server/tools/misc/describe_cache_engine_versions.py
awslabs/elasticache_mcp_server/tools/misc/describe_engine_default_parameters.py
awslabs/elasticache_mcp_server/tools/misc/describe_events.py
awslabs_elasticache_mcp_server-0.1.12.dist-info/METADATA
awslabs_elasticache_mcp_server-0.1.12.dist-info/WHEEL
awslabs_elasticache_mcp_server-0.1.12.dist-info/entry_points.txt
awslabs_elasticache_mcp_server-0.1.12.dist-info/licenses/LICENSE
awslabs_elasticache_mcp_server-0.1.12.dist-info/licenses/NOTICE
awslabs_elasticache_mcp_server-0.1.12.dist-info/RECORD
